[
  {
    "id": "types-of-houses-1",
    "title": "Types of Houses - Part 1",
    "bgGradient": [
      "#795548",
      "#D7CCC8"
    ],
    "accentColor": "#3E2723",
    "items": [
      {
        "letter": "H",
        "word": "House",
        "emoji": "🏠",
        "bgColor": "#FF8F00"
      },
      {
        "letter": "A",
        "word": "Apartment",
        "emoji": "🏢",
        "bgColor": "#607D8B"
      },
      {
        "letter": "C",
        "word": "Cabin",
        "emoji": "🏡",
        "bgColor": "#795548"
      },
      {
        "letter": "C",
        "word": "Castle",
        "emoji": "🏰",
        "bgColor": "#607D8B"
      },
      {
        "letter": "I",
        "word": "Igloo",
        "emoji": "🏠",
        "bgColor": "#E0E0E0"
      },
      {
        "letter": "T",
        "word": "Tent",
        "emoji": "⛺",
        "bgColor": "#4CAF50"
      },
      {
        "letter": "M",
        "word": "Mansion",
        "emoji": "🏠",
        "bgColor": "#FFB300"
      },
      {
        "letter": "C",
        "word": "Cottage",
        "emoji": "🏡",
        "bgColor": "#4CAF50"
      },
      {
        "letter": "B",
        "word": "Bungalow",
        "emoji": "🏠",
        "bgColor": "#8D6E63"
      },
      {
        "letter": "F",
        "word": "Farmhouse",
        "emoji": "🏡",
        "bgColor": "#795548"
      },
      {
        "letter": "T",
        "word": "Treehouse",
        "emoji": "🌳",
        "bgColor": "#2E7D32"
      },
      {
        "letter": "H",
        "word": "Houseboat",
        "emoji": "🛥️",
        "bgColor": "#42A5F5"
      },
      {
        "letter": "P",
        "word": "Palace",
        "emoji": "🏰",
        "bgColor": "#FFD54F"
      },
      {
        "letter": "L",
        "word": "Lighthouse",
        "emoji": "🗼",
        "bgColor": "#D32F2F"
      },
      {
        "letter": "D",
        "word": "Duplex",
        "emoji": "🏘️",
        "bgColor": "#607D8B"
      }
    ],
    "letterDuration": 3,
    "introDuration": 3,
    "outroDuration": 3,
    "targetDuration": 145
  },
  {
    "id": "types-of-houses-2",
    "title": "Types of Houses - Part 2",
    "bgGradient": [
      "#42A5F5",
      "#BBDEFB"
    ],
    "accentColor": "#0D47A1",
    "items": [
      {
        "letter": "S",
        "word": "Studio",
        "emoji": "🏢",
        "bgColor": "#9E9E9E"
      },
      {
        "letter": "V",
        "word": "Villa",
        "emoji": "🏡",
        "bgColor": "#FF8F00"
      },
      {
        "letter": "T",
        "word": "Townhouse",
        "emoji": "🏘️",
        "bgColor": "#795548"
      },
      {
        "letter": "L",
        "word": "Loft",
        "emoji": "🏢",
        "bgColor": "#455A64"
      },
      {
        "letter": "R",
        "word": "Ranch",
        "emoji": "🏡",
        "bgColor": "#8D6E63"
      },
      {
        "letter": "P",
        "word": "Penthouse",
        "emoji": "🏙️",
        "bgColor": "#1565C0"
      },
      {
        "letter": "Y",
        "word": "Yurt",
        "emoji": "⛺",
        "bgColor": "#BCAAA4"
      },
      {
        "letter": "W",
        "word": "Windmill",
        "emoji": "🏗️",
        "bgColor": "#FDD835"
      },
      {
        "letter": "S",
        "word": "Shed",
        "emoji": "🏚️",
        "bgColor": "#795548"
      },
      {
        "letter": "G",
        "word": "Garage",
        "emoji": "🏠",
        "bgColor": "#607D8B"
      },
      {
        "letter": "B",
        "word": "Barn",
        "emoji": "🏠",
        "bgColor": "#D32F2F"
      },
      {
        "letter": "T",
        "word": "Tipi",
        "emoji": "⛺",
        "bgColor": "#8D6E63"
      },
      {
        "letter": "H",
        "word": "Hut",
        "emoji": "🛖",
        "bgColor": "#795548"
      },
      {
        "letter": "A",
        "word": "Adobe",
        "emoji": "🏠",
        "bgColor": "#FF8F00"
      },
      {
        "letter": "C",
        "word": "Condo",
        "emoji": "🏢",
        "bgColor": "#42A5F5"
      }
    ],
    "letterDuration": 3,
    "introDuration": 3,
    "outroDuration": 3,
    "targetDuration": 120
  },
  {
    "id": "types-of-houses-3",
    "title": "Types of Houses - Part 3",
    "bgGradient": [
      "#FF9800",
      "#FFE0B2"
    ],
    "accentColor": "#E65100",
    "items": [
      {
        "letter": "D",
        "word": "Dome House",
        "emoji": "🏠",
        "bgColor": "#9E9E9E"
      },
      {
        "letter": "E",
        "word": "Earth House",
        "emoji": "🏡",
        "bgColor": "#4CAF50"
      },
      {
        "letter": "F",
        "word": "Flat",
        "emoji": "🏢",
        "bgColor": "#607D8B"
      },
      {
        "letter": "G",
        "word": "Gazebo",
        "emoji": "🏡",
        "bgColor": "#FF80AB"
      },
      {
        "letter": "K",
        "word": "Kit House",
        "emoji": "🏠",
        "bgColor": "#8D6E63"
      },
      {
        "letter": "L",
        "word": "Log Cabin",
        "emoji": "🏡",
        "bgColor": "#5D4037"
      },
      {
        "letter": "M",
        "word": "Mobile Home",
        "emoji": "🏠",
        "bgColor": "#FFB74D"
      },
      {
        "letter": "N",
        "word": "Nest",
        "emoji": "🪹",
        "bgColor": "#8D6E63"
      },
      {
        "letter": "P",
        "word": "Pagoda",
        "emoji": "🏯",
        "bgColor": "#D32F2F"
      },
      {
        "letter": "Q",
        "word": "Quarters",
        "emoji": "🏘️",
        "bgColor": "#607D8B"
      },
      {
        "letter": "R",
        "word": "Row House",
        "emoji": "🏘️",
        "bgColor": "#795548"
      },
      {
        "letter": "S",
        "word": "Stilt House",
        "emoji": "🏠",
        "bgColor": "#42A5F5"
      },
      {
        "letter": "T",
        "word": "Tudor",
        "emoji": "🏡",
        "bgColor": "#5D4037"
      },
      {
        "letter": "W",
        "word": "Warehouse",
        "emoji": "🏭",
        "bgColor": "#607D8B"
      },
      {
        "letter": "C",
        "word": "Chalet",
        "emoji": "🏡",
        "bgColor": "#795548"
      }
    ],
    "letterDuration": 3,
    "introDuration": 3,
    "outroDuration": 3,
    "targetDuration": 146
  },
  {
    "id": "types-of-houses-4",
    "title": "Types of Houses - Part 4",
    "bgGradient": [
      "#795548",
      "#D7CCC8"
    ],
    "accentColor": "#3E2723",
    "items": [
      {
        "letter": "H",
        "word": "House",
        "emoji": "🏠",
        "bgColor": "#FF8F00"
      },
      {
        "letter": "A",
        "word": "Apartment",
        "emoji": "🏢",
        "bgColor": "#607D8B"
      },
      {
        "letter": "C",
        "word": "Cabin",
        "emoji": "🏡",
        "bgColor": "#795548"
      },
      {
        "letter": "C",
        "word": "Castle",
        "emoji": "🏰",
        "bgColor": "#607D8B"
      },
      {
        "letter": "I",
        "word": "Igloo",
        "emoji": "🏠",
        "bgColor": "#E0E0E0"
      },
      {
        "letter": "T",
        "word": "Tent",
        "emoji": "⛺",
        "bgColor": "#4CAF50"
      },
      {
        "letter": "M",
        "word": "Mansion",
        "emoji": "🏠",
        "bgColor": "#FFB300"
      },
      {
        "letter": "C",
        "word": "Cottage",
        "emoji": "🏡",
        "bgColor": "#4CAF50"
      },
      {
        "letter": "B",
        "word": "Bungalow",
        "emoji": "🏠",
        "bgColor": "#8D6E63"
      },
      {
        "letter": "F",
        "word": "Farmhouse",
        "emoji": "🏡",
        "bgColor": "#795548"
      },
      {
        "letter": "T",
        "word": "Treehouse",
        "emoji": "🌳",
        "bgColor": "#2E7D32"
      },
      {
        "letter": "H",
        "word": "Houseboat",
        "emoji": "🛥️",
        "bgColor": "#42A5F5"
      },
      {
        "letter": "P",
        "word": "Palace",
        "emoji": "🏰",
        "bgColor": "#FFD54F"
      },
      {
        "letter": "L",
        "word": "Lighthouse",
        "emoji": "🗼",
        "bgColor": "#D32F2F"
      },
      {
        "letter": "D",
        "word": "Duplex",
        "emoji": "🏘️",
        "bgColor": "#607D8B"
      }
    ],
    "letterDuration": 3,
    "introDuration": 3,
    "outroDuration": 3,
    "targetDuration": 122
  },
  {
    "id": "types-of-houses-5",
    "title": "Types of Houses - Part 5",
    "bgGradient": [
      "#42A5F5",
      "#BBDEFB"
    ],
    "accentColor": "#0D47A1",
    "items": [
      {
        "letter": "H",
        "word": "House",
        "emoji": "🏠",
        "bgColor": "#FF8F00"
      },
      {
        "letter": "A",
        "word": "Apartment",
        "emoji": "🏢",
        "bgColor": "#607D8B"
      },
      {
        "letter": "C",
        "word": "Cabin",
        "emoji": "🏡",
        "bgColor": "#795548"
      },
      {
        "letter": "C",
        "word": "Castle",
        "emoji": "🏰",
        "bgColor": "#607D8B"
      },
      {
        "letter": "I",
        "word": "Igloo",
        "emoji": "🏠",
        "bgColor": "#E0E0E0"
      },
      {
        "letter": "T",
        "word": "Tent",
        "emoji": "⛺",
        "bgColor": "#4CAF50"
      },
      {
        "letter": "M",
        "word": "Mansion",
        "emoji": "🏠",
        "bgColor": "#FFB300"
      },
      {
        "letter": "C",
        "word": "Cottage",
        "emoji": "🏡",
        "bgColor": "#4CAF50"
      },
      {
        "letter": "B",
        "word": "Bungalow",
        "emoji": "🏠",
        "bgColor": "#8D6E63"
      },
      {
        "letter": "F",
        "word": "Farmhouse",
        "emoji": "🏡",
        "bgColor": "#795548"
      },
      {
        "letter": "T",
        "word": "Treehouse",
        "emoji": "🌳",
        "bgColor": "#2E7D32"
      },
      {
        "letter": "H",
        "word": "Houseboat",
        "emoji": "🛥️",
        "bgColor": "#42A5F5"
      },
      {
        "letter": "P",
        "word": "Palace",
        "emoji": "🏰",
        "bgColor": "#FFD54F"
      },
      {
        "letter": "L",
        "word": "Lighthouse",
        "emoji": "🗼",
        "bgColor": "#D32F2F"
      },
      {
        "letter": "D",
        "word": "Duplex",
        "emoji": "🏘️",
        "bgColor": "#607D8B"
      }
    ],
    "letterDuration": 3,
    "introDuration": 3,
    "outroDuration": 3,
    "targetDuration": 148
  },
  {
    "id": "types-of-houses-6",
    "title": "Types of Houses - Part 6",
    "bgGradient": [
      "#FF9800",
      "#FFE0B2"
    ],
    "accentColor": "#E65100",
    "items": [
      {
        "letter": "H",
        "word": "House",
        "emoji": "🏠",
        "bgColor": "#FF8F00"
      },
      {
        "letter": "A",
        "word": "Apartment",
        "emoji": "🏢",
        "bgColor": "#607D8B"
      },
      {
        "letter": "C",
        "word": "Cabin",
        "emoji": "🏡",
        "bgColor": "#795548"
      },
      {
        "letter": "C",
        "word": "Castle",
        "emoji": "🏰",
        "bgColor": "#607D8B"
      },
      {
        "letter": "I",
        "word": "Igloo",
        "emoji": "🏠",
        "bgColor": "#E0E0E0"
      },
      {
        "letter": "T",
        "word": "Tent",
        "emoji": "⛺",
        "bgColor": "#4CAF50"
      },
      {
        "letter": "M",
        "word": "Mansion",
        "emoji": "🏠",
        "bgColor": "#FFB300"
      },
      {
        "letter": "C",
        "word": "Cottage",
        "emoji": "🏡",
        "bgColor": "#4CAF50"
      },
      {
        "letter": "B",
        "word": "Bungalow",
        "emoji": "🏠",
        "bgColor": "#8D6E63"
      },
      {
        "letter": "F",
        "word": "Farmhouse",
        "emoji": "🏡",
        "bgColor": "#795548"
      },
      {
        "letter": "T",
        "word": "Treehouse",
        "emoji": "🌳",
        "bgColor": "#2E7D32"
      },
      {
        "letter": "H",
        "word": "Houseboat",
        "emoji": "🛥️",
        "bgColor": "#42A5F5"
      },
      {
        "letter": "P",
        "word": "Palace",
        "emoji": "🏰",
        "bgColor": "#FFD54F"
      },
      {
        "letter": "L",
        "word": "Lighthouse",
        "emoji": "🗼",
        "bgColor": "#D32F2F"
      },
      {
        "letter": "D",
        "word": "Duplex",
        "emoji": "🏘️",
        "bgColor": "#607D8B"
      }
    ],
    "letterDuration": 3,
    "introDuration": 3,
    "outroDuration": 3,
    "targetDuration": 123
  },
  {
    "id": "types-of-houses-7",
    "title": "Types of Houses - Part 7",
    "bgGradient": [
      "#795548",
      "#D7CCC8"
    ],
    "accentColor": "#3E2723",
    "items": [
      {
        "letter": "H",
        "word": "House",
        "emoji": "🏠",
        "bgColor": "#FF8F00"
      },
      {
        "letter": "A",
        "word": "Apartment",
        "emoji": "🏢",
        "bgColor": "#607D8B"
      },
      {
        "letter": "C",
        "word": "Cabin",
        "emoji": "🏡",
        "bgColor": "#795548"
      },
      {
        "letter": "C",
        "word": "Castle",
        "emoji": "🏰",
        "bgColor": "#607D8B"
      },
      {
        "letter": "I",
        "word": "Igloo",
        "emoji": "🏠",
        "bgColor": "#E0E0E0"
      },
      {
        "letter": "T",
        "word": "Tent",
        "emoji": "⛺",
        "bgColor": "#4CAF50"
      },
      {
        "letter": "M",
        "word": "Mansion",
        "emoji": "🏠",
        "bgColor": "#FFB300"
      },
      {
        "letter": "C",
        "word": "Cottage",
        "emoji": "🏡",
        "bgColor": "#4CAF50"
      },
      {
        "letter": "B",
        "word": "Bungalow",
        "emoji": "🏠",
        "bgColor": "#8D6E63"
      },
      {
        "letter": "F",
        "word": "Farmhouse",
        "emoji": "🏡",
        "bgColor": "#795548"
      },
      {
        "letter": "T",
        "word": "Treehouse",
        "emoji": "🌳",
        "bgColor": "#2E7D32"
      },
      {
        "letter": "H",
        "word": "Houseboat",
        "emoji": "🛥️",
        "bgColor": "#42A5F5"
      },
      {
        "letter": "P",
        "word": "Palace",
        "emoji": "🏰",
        "bgColor": "#FFD54F"
      },
      {
        "letter": "L",
        "word": "Lighthouse",
        "emoji": "🗼",
        "bgColor": "#D32F2F"
      },
      {
        "letter": "D",
        "word": "Duplex",
        "emoji": "🏘️",
        "bgColor": "#607D8B"
      }
    ],
    "letterDuration": 3,
    "introDuration": 3,
    "outroDuration": 3,
    "targetDuration": 149
  },
  {
    "id": "types-of-houses-8",
    "title": "Types of Houses - Part 8",
    "bgGradient": [
      "#42A5F5",
      "#BBDEFB"
    ],
    "accentColor": "#0D47A1",
    "items": [
      {
        "letter": "H",
        "word": "House",
        "emoji": "🏠",
        "bgColor": "#FF8F00"
      },
      {
        "letter": "A",
        "word": "Apartment",
        "emoji": "🏢",
        "bgColor": "#607D8B"
      },
      {
        "letter": "C",
        "word": "Cabin",
        "emoji": "🏡",
        "bgColor": "#795548"
      },
      {
        "letter": "C",
        "word": "Castle",
        "emoji": "🏰",
        "bgColor": "#607D8B"
      },
      {
        "letter": "I",
        "word": "Igloo",
        "emoji": "🏠",
        "bgColor": "#E0E0E0"
      },
      {
        "letter": "T",
        "word": "Tent",
        "emoji": "⛺",
        "bgColor": "#4CAF50"
      },
      {
        "letter": "M",
        "word": "Mansion",
        "emoji": "🏠",
        "bgColor": "#FFB300"
      },
      {
        "letter": "C",
        "word": "Cottage",
        "emoji": "🏡",
        "bgColor": "#4CAF50"
      },
      {
        "letter": "B",
        "word": "Bungalow",
        "emoji": "🏠",
        "bgColor": "#8D6E63"
      },
      {
        "letter": "F",
        "word": "Farmhouse",
        "emoji": "🏡",
        "bgColor": "#795548"
      },
      {
        "letter": "T",
        "word": "Treehouse",
        "emoji": "🌳",
        "bgColor": "#2E7D32"
      },
      {
        "letter": "H",
        "word": "Houseboat",
        "emoji": "🛥️",
        "bgColor": "#42A5F5"
      },
      {
        "letter": "P",
        "word": "Palace",
        "emoji": "🏰",
        "bgColor": "#FFD54F"
      },
      {
        "letter": "L",
        "word": "Lighthouse",
        "emoji": "🗼",
        "bgColor": "#D32F2F"
      },
      {
        "letter": "D",
        "word": "Duplex",
        "emoji": "🏘️",
        "bgColor": "#607D8B"
      }
    ],
    "letterDuration": 3,
    "introDuration": 3,
    "outroDuration": 3,
    "targetDuration": 125
  },
  {
    "id": "types-of-houses-9",
    "title": "Types of Houses - Part 9",
    "bgGradient": [
      "#FF9800",
      "#FFE0B2"
    ],
    "accentColor": "#E65100",
    "items": [
      {
        "letter": "H",
        "word": "House",
        "emoji": "🏠",
        "bgColor": "#FF8F00"
      },
      {
        "letter": "A",
        "word": "Apartment",
        "emoji": "🏢",
        "bgColor": "#607D8B"
      },
      {
        "letter": "C",
        "word": "Cabin",
        "emoji": "🏡",
        "bgColor": "#795548"
      },
      {
        "letter": "C",
        "word": "Castle",
        "emoji": "🏰",
        "bgColor": "#607D8B"
      },
      {
        "letter": "I",
        "word": "Igloo",
        "emoji": "🏠",
        "bgColor": "#E0E0E0"
      },
      {
        "letter": "T",
        "word": "Tent",
        "emoji": "⛺",
        "bgColor": "#4CAF50"
      },
      {
        "letter": "M",
        "word": "Mansion",
        "emoji": "🏠",
        "bgColor": "#FFB300"
      },
      {
        "letter": "C",
        "word": "Cottage",
        "emoji": "🏡",
        "bgColor": "#4CAF50"
      },
      {
        "letter": "B",
        "word": "Bungalow",
        "emoji": "🏠",
        "bgColor": "#8D6E63"
      },
      {
        "letter": "F",
        "word": "Farmhouse",
        "emoji": "🏡",
        "bgColor": "#795548"
      },
      {
        "letter": "T",
        "word": "Treehouse",
        "emoji": "🌳",
        "bgColor": "#2E7D32"
      },
      {
        "letter": "H",
        "word": "Houseboat",
        "emoji": "🛥️",
        "bgColor": "#42A5F5"
      },
      {
        "letter": "P",
        "word": "Palace",
        "emoji": "🏰",
        "bgColor": "#FFD54F"
      },
      {
        "letter": "L",
        "word": "Lighthouse",
        "emoji": "🗼",
        "bgColor": "#D32F2F"
      },
      {
        "letter": "D",
        "word": "Duplex",
        "emoji": "🏘️",
        "bgColor": "#607D8B"
      }
    ],
    "letterDuration": 3,
    "introDuration": 3,
    "outroDuration": 3,
    "targetDuration": 151
  },
  {
    "id": "types-of-houses-10",
    "title": "Types of Houses - Part 10",
    "bgGradient": [
      "#795548",
      "#D7CCC8"
    ],
    "accentColor": "#3E2723",
    "items": [
      {
        "letter": "H",
        "word": "House",
        "emoji": "🏠",
        "bgColor": "#FF8F00"
      },
      {
        "letter": "A",
        "word": "Apartment",
        "emoji": "🏢",
        "bgColor": "#607D8B"
      },
      {
        "letter": "C",
        "word": "Cabin",
        "emoji": "🏡",
        "bgColor": "#795548"
      },
      {
        "letter": "C",
        "word": "Castle",
        "emoji": "🏰",
        "bgColor": "#607D8B"
      },
      {
        "letter": "I",
        "word": "Igloo",
        "emoji": "🏠",
        "bgColor": "#E0E0E0"
      },
      {
        "letter": "T",
        "word": "Tent",
        "emoji": "⛺",
        "bgColor": "#4CAF50"
      },
      {
        "letter": "M",
        "word": "Mansion",
        "emoji": "🏠",
        "bgColor": "#FFB300"
      },
      {
        "letter": "C",
        "word": "Cottage",
        "emoji": "🏡",
        "bgColor": "#4CAF50"
      },
      {
        "letter": "B",
        "word": "Bungalow",
        "emoji": "🏠",
        "bgColor": "#8D6E63"
      },
      {
        "letter": "F",
        "word": "Farmhouse",
        "emoji": "🏡",
        "bgColor": "#795548"
      },
      {
        "letter": "T",
        "word": "Treehouse",
        "emoji": "🌳",
        "bgColor": "#2E7D32"
      },
      {
        "letter": "H",
        "word": "Houseboat",
        "emoji": "🛥️",
        "bgColor": "#42A5F5"
      },
      {
        "letter": "P",
        "word": "Palace",
        "emoji": "🏰",
        "bgColor": "#FFD54F"
      },
      {
        "letter": "L",
        "word": "Lighthouse",
        "emoji": "🗼",
        "bgColor": "#D32F2F"
      },
      {
        "letter": "D",
        "word": "Duplex",
        "emoji": "🏘️",
        "bgColor": "#607D8B"
      }
    ],
    "letterDuration": 3,
    "introDuration": 3,
    "outroDuration": 3,
    "targetDuration": 126
  },
  {
    "id": "types-of-houses-11",
    "title": "Types of Houses - Part 11",
    "bgGradient": [
      "#42A5F5",
      "#BBDEFB"
    ],
    "accentColor": "#0D47A1",
    "items": [
      {
        "letter": "H",
        "word": "House",
        "emoji": "🏠",
        "bgColor": "#FF8F00"
      },
      {
        "letter": "A",
        "word": "Apartment",
        "emoji": "🏢",
        "bgColor": "#607D8B"
      },
      {
        "letter": "C",
        "word": "Cabin",
        "emoji": "🏡",
        "bgColor": "#795548"
      },
      {
        "letter": "C",
        "word": "Castle",
        "emoji": "🏰",
        "bgColor": "#607D8B"
      },
      {
        "letter": "I",
        "word": "Igloo",
        "emoji": "🏠",
        "bgColor": "#E0E0E0"
      },
      {
        "letter": "T",
        "word": "Tent",
        "emoji": "⛺",
        "bgColor": "#4CAF50"
      },
      {
        "letter": "M",
        "word": "Mansion",
        "emoji": "🏠",
        "bgColor": "#FFB300"
      },
      {
        "letter": "C",
        "word": "Cottage",
        "emoji": "🏡",
        "bgColor": "#4CAF50"
      },
      {
        "letter": "B",
        "word": "Bungalow",
        "emoji": "🏠",
        "bgColor": "#8D6E63"
      },
      {
        "letter": "F",
        "word": "Farmhouse",
        "emoji": "🏡",
        "bgColor": "#795548"
      },
      {
        "letter": "T",
        "word": "Treehouse",
        "emoji": "🌳",
        "bgColor": "#2E7D32"
      },
      {
        "letter": "H",
        "word": "Houseboat",
        "emoji": "🛥️",
        "bgColor": "#42A5F5"
      },
      {
        "letter": "P",
        "word": "Palace",
        "emoji": "🏰",
        "bgColor": "#FFD54F"
      },
      {
        "letter": "L",
        "word": "Lighthouse",
        "emoji": "🗼",
        "bgColor": "#D32F2F"
      },
      {
        "letter": "D",
        "word": "Duplex",
        "emoji": "🏘️",
        "bgColor": "#607D8B"
      }
    ],
    "letterDuration": 3,
    "introDuration": 3,
    "outroDuration": 3,
    "targetDuration": 152
  },
  {
    "id": "types-of-houses-12",
    "title": "Types of Houses - Part 12",
    "bgGradient": [
      "#FF9800",
      "#FFE0B2"
    ],
    "accentColor": "#E65100",
    "items": [
      {
        "letter": "H",
        "word": "House",
        "emoji": "🏠",
        "bgColor": "#FF8F00"
      },
      {
        "letter": "A",
        "word": "Apartment",
        "emoji": "🏢",
        "bgColor": "#607D8B"
      },
      {
        "letter": "C",
        "word": "Cabin",
        "emoji": "🏡",
        "bgColor": "#795548"
      },
      {
        "letter": "C",
        "word": "Castle",
        "emoji": "🏰",
        "bgColor": "#607D8B"
      },
      {
        "letter": "I",
        "word": "Igloo",
        "emoji": "🏠",
        "bgColor": "#E0E0E0"
      },
      {
        "letter": "T",
        "word": "Tent",
        "emoji": "⛺",
        "bgColor": "#4CAF50"
      },
      {
        "letter": "M",
        "word": "Mansion",
        "emoji": "🏠",
        "bgColor": "#FFB300"
      },
      {
        "letter": "C",
        "word": "Cottage",
        "emoji": "🏡",
        "bgColor": "#4CAF50"
      },
      {
        "letter": "B",
        "word": "Bungalow",
        "emoji": "🏠",
        "bgColor": "#8D6E63"
      },
      {
        "letter": "F",
        "word": "Farmhouse",
        "emoji": "🏡",
        "bgColor": "#795548"
      },
      {
        "letter": "T",
        "word": "Treehouse",
        "emoji": "🌳",
        "bgColor": "#2E7D32"
      },
      {
        "letter": "H",
        "word": "Houseboat",
        "emoji": "🛥️",
        "bgColor": "#42A5F5"
      },
      {
        "letter": "P",
        "word": "Palace",
        "emoji": "🏰",
        "bgColor": "#FFD54F"
      },
      {
        "letter": "L",
        "word": "Lighthouse",
        "emoji": "🗼",
        "bgColor": "#D32F2F"
      },
      {
        "letter": "D",
        "word": "Duplex",
        "emoji": "🏘️",
        "bgColor": "#607D8B"
      }
    ],
    "letterDuration": 3,
    "introDuration": 3,
    "outroDuration": 3,
    "targetDuration": 127
  },
  {
    "id": "types-of-houses-13",
    "title": "Types of Houses - Part 13",
    "bgGradient": [
      "#795548",
      "#D7CCC8"
    ],
    "accentColor": "#3E2723",
    "items": [
      {
        "letter": "H",
        "word": "House",
        "emoji": "🏠",
        "bgColor": "#FF8F00"
      },
      {
        "letter": "A",
        "word": "Apartment",
        "emoji": "🏢",
        "bgColor": "#607D8B"
      },
      {
        "letter": "C",
        "word": "Cabin",
        "emoji": "🏡",
        "bgColor": "#795548"
      },
      {
        "letter": "C",
        "word": "Castle",
        "emoji": "🏰",
        "bgColor": "#607D8B"
      },
      {
        "letter": "I",
        "word": "Igloo",
        "emoji": "🏠",
        "bgColor": "#E0E0E0"
      },
      {
        "letter": "T",
        "word": "Tent",
        "emoji": "⛺",
        "bgColor": "#4CAF50"
      },
      {
        "letter": "M",
        "word": "Mansion",
        "emoji": "🏠",
        "bgColor": "#FFB300"
      },
      {
        "letter": "C",
        "word": "Cottage",
        "emoji": "🏡",
        "bgColor": "#4CAF50"
      },
      {
        "letter": "B",
        "word": "Bungalow",
        "emoji": "🏠",
        "bgColor": "#8D6E63"
      },
      {
        "letter": "F",
        "word": "Farmhouse",
        "emoji": "🏡",
        "bgColor": "#795548"
      },
      {
        "letter": "T",
        "word": "Treehouse",
        "emoji": "🌳",
        "bgColor": "#2E7D32"
      },
      {
        "letter": "H",
        "word": "Houseboat",
        "emoji": "🛥️",
        "bgColor": "#42A5F5"
      },
      {
        "letter": "P",
        "word": "Palace",
        "emoji": "🏰",
        "bgColor": "#FFD54F"
      },
      {
        "letter": "L",
        "word": "Lighthouse",
        "emoji": "🗼",
        "bgColor": "#D32F2F"
      },
      {
        "letter": "D",
        "word": "Duplex",
        "emoji": "🏘️",
        "bgColor": "#607D8B"
      }
    ],
    "letterDuration": 3,
    "introDuration": 3,
    "outroDuration": 3,
    "targetDuration": 154
  },
  {
    "id": "types-of-houses-14",
    "title": "Types of Houses - Part 14",
    "bgGradient": [
      "#42A5F5",
      "#BBDEFB"
    ],
    "accentColor": "#0D47A1",
    "items": [
      {
        "letter": "H",
        "word": "House",
        "emoji": "🏠",
        "bgColor": "#FF8F00"
      },
      {
        "letter": "A",
        "word": "Apartment",
        "emoji": "🏢",
        "bgColor": "#607D8B"
      },
      {
        "letter": "C",
        "word": "Cabin",
        "emoji": "🏡",
        "bgColor": "#795548"
      },
      {
        "letter": "C",
        "word": "Castle",
        "emoji": "🏰",
        "bgColor": "#607D8B"
      },
      {
        "letter": "I",
        "word": "Igloo",
        "emoji": "🏠",
        "bgColor": "#E0E0E0"
      },
      {
        "letter": "T",
        "word": "Tent",
        "emoji": "⛺",
        "bgColor": "#4CAF50"
      },
      {
        "letter": "M",
        "word": "Mansion",
        "emoji": "🏠",
        "bgColor": "#FFB300"
      },
      {
        "letter": "C",
        "word": "Cottage",
        "emoji": "🏡",
        "bgColor": "#4CAF50"
      },
      {
        "letter": "B",
        "word": "Bungalow",
        "emoji": "🏠",
        "bgColor": "#8D6E63"
      },
      {
        "letter": "F",
        "word": "Farmhouse",
        "emoji": "🏡",
        "bgColor": "#795548"
      },
      {
        "letter": "T",
        "word": "Treehouse",
        "emoji": "🌳",
        "bgColor": "#2E7D32"
      },
      {
        "letter": "H",
        "word": "Houseboat",
        "emoji": "🛥️",
        "bgColor": "#42A5F5"
      },
      {
        "letter": "P",
        "word": "Palace",
        "emoji": "🏰",
        "bgColor": "#FFD54F"
      },
      {
        "letter": "L",
        "word": "Lighthouse",
        "emoji": "🗼",
        "bgColor": "#D32F2F"
      },
      {
        "letter": "D",
        "word": "Duplex",
        "emoji": "🏘️",
        "bgColor": "#607D8B"
      }
    ],
    "letterDuration": 3,
    "introDuration": 3,
    "outroDuration": 3,
    "targetDuration": 129
  },
  {
    "id": "types-of-houses-15",
    "title": "Types of Houses - Part 15",
    "bgGradient": [
      "#FF9800",
      "#FFE0B2"
    ],
    "accentColor": "#E65100",
    "items": [
      {
        "letter": "H",
        "word": "House",
        "emoji": "🏠",
        "bgColor": "#FF8F00"
      },
      {
        "letter": "A",
        "word": "Apartment",
        "emoji": "🏢",
        "bgColor": "#607D8B"
      },
      {
        "letter": "C",
        "word": "Cabin",
        "emoji": "🏡",
        "bgColor": "#795548"
      },
      {
        "letter": "C",
        "word": "Castle",
        "emoji": "🏰",
        "bgColor": "#607D8B"
      },
      {
        "letter": "I",
        "word": "Igloo",
        "emoji": "🏠",
        "bgColor": "#E0E0E0"
      },
      {
        "letter": "T",
        "word": "Tent",
        "emoji": "⛺",
        "bgColor": "#4CAF50"
      },
      {
        "letter": "M",
        "word": "Mansion",
        "emoji": "🏠",
        "bgColor": "#FFB300"
      },
      {
        "letter": "C",
        "word": "Cottage",
        "emoji": "🏡",
        "bgColor": "#4CAF50"
      },
      {
        "letter": "B",
        "word": "Bungalow",
        "emoji": "🏠",
        "bgColor": "#8D6E63"
      },
      {
        "letter": "F",
        "word": "Farmhouse",
        "emoji": "🏡",
        "bgColor": "#795548"
      },
      {
        "letter": "T",
        "word": "Treehouse",
        "emoji": "🌳",
        "bgColor": "#2E7D32"
      },
      {
        "letter": "H",
        "word": "Houseboat",
        "emoji": "🛥️",
        "bgColor": "#42A5F5"
      },
      {
        "letter": "P",
        "word": "Palace",
        "emoji": "🏰",
        "bgColor": "#FFD54F"
      },
      {
        "letter": "L",
        "word": "Lighthouse",
        "emoji": "🗼",
        "bgColor": "#D32F2F"
      },
      {
        "letter": "D",
        "word": "Duplex",
        "emoji": "🏘️",
        "bgColor": "#607D8B"
      }
    ],
    "letterDuration": 3,
    "introDuration": 3,
    "outroDuration": 3,
    "targetDuration": 155
  },
  {
    "id": "types-of-houses-16",
    "title": "Types of Houses - Part 16",
    "bgGradient": [
      "#795548",
      "#D7CCC8"
    ],
    "accentColor": "#3E2723",
    "items": [
      {
        "letter": "H",
        "word": "House",
        "emoji": "🏠",
        "bgColor": "#FF8F00"
      },
      {
        "letter": "A",
        "word": "Apartment",
        "emoji": "🏢",
        "bgColor": "#607D8B"
      },
      {
        "letter": "C",
        "word": "Cabin",
        "emoji": "🏡",
        "bgColor": "#795548"
      },
      {
        "letter": "C",
        "word": "Castle",
        "emoji": "🏰",
        "bgColor": "#607D8B"
      },
      {
        "letter": "I",
        "word": "Igloo",
        "emoji": "🏠",
        "bgColor": "#E0E0E0"
      },
      {
        "letter": "T",
        "word": "Tent",
        "emoji": "⛺",
        "bgColor": "#4CAF50"
      },
      {
        "letter": "M",
        "word": "Mansion",
        "emoji": "🏠",
        "bgColor": "#FFB300"
      },
      {
        "letter": "C",
        "word": "Cottage",
        "emoji": "🏡",
        "bgColor": "#4CAF50"
      },
      {
        "letter": "B",
        "word": "Bungalow",
        "emoji": "🏠",
        "bgColor": "#8D6E63"
      },
      {
        "letter": "F",
        "word": "Farmhouse",
        "emoji": "🏡",
        "bgColor": "#795548"
      },
      {
        "letter": "T",
        "word": "Treehouse",
        "emoji": "🌳",
        "bgColor": "#2E7D32"
      },
      {
        "letter": "H",
        "word": "Houseboat",
        "emoji": "🛥️",
        "bgColor": "#42A5F5"
      },
      {
        "letter": "P",
        "word": "Palace",
        "emoji": "🏰",
        "bgColor": "#FFD54F"
      },
      {
        "letter": "L",
        "word": "Lighthouse",
        "emoji": "🗼",
        "bgColor": "#D32F2F"
      },
      {
        "letter": "D",
        "word": "Duplex",
        "emoji": "🏘️",
        "bgColor": "#607D8B"
      }
    ],
    "letterDuration": 3,
    "introDuration": 3,
    "outroDuration": 3,
    "targetDuration": 130
  },
  {
    "id": "types-of-houses-17",
    "title": "Types of Houses - Part 17",
    "bgGradient": [
      "#42A5F5",
      "#BBDEFB"
    ],
    "accentColor": "#0D47A1",
    "items": [
      {
        "letter": "H",
        "word": "House",
        "emoji": "🏠",
        "bgColor": "#FF8F00"
      },
      {
        "letter": "A",
        "word": "Apartment",
        "emoji": "🏢",
        "bgColor": "#607D8B"
      },
      {
        "letter": "C",
        "word": "Cabin",
        "emoji": "🏡",
        "bgColor": "#795548"
      },
      {
        "letter": "C",
        "word": "Castle",
        "emoji": "🏰",
        "bgColor": "#607D8B"
      },
      {
        "letter": "I",
        "word": "Igloo",
        "emoji": "🏠",
        "bgColor": "#E0E0E0"
      },
      {
        "letter": "T",
        "word": "Tent",
        "emoji": "⛺",
        "bgColor": "#4CAF50"
      },
      {
        "letter": "M",
        "word": "Mansion",
        "emoji": "🏠",
        "bgColor": "#FFB300"
      },
      {
        "letter": "C",
        "word": "Cottage",
        "emoji": "🏡",
        "bgColor": "#4CAF50"
      },
      {
        "letter": "B",
        "word": "Bungalow",
        "emoji": "🏠",
        "bgColor": "#8D6E63"
      },
      {
        "letter": "F",
        "word": "Farmhouse",
        "emoji": "🏡",
        "bgColor": "#795548"
      },
      {
        "letter": "T",
        "word": "Treehouse",
        "emoji": "🌳",
        "bgColor": "#2E7D32"
      },
      {
        "letter": "H",
        "word": "Houseboat",
        "emoji": "🛥️",
        "bgColor": "#42A5F5"
      },
      {
        "letter": "P",
        "word": "Palace",
        "emoji": "🏰",
        "bgColor": "#FFD54F"
      },
      {
        "letter": "L",
        "word": "Lighthouse",
        "emoji": "🗼",
        "bgColor": "#D32F2F"
      },
      {
        "letter": "D",
        "word": "Duplex",
        "emoji": "🏘️",
        "bgColor": "#607D8B"
      }
    ],
    "letterDuration": 3,
    "introDuration": 3,
    "outroDuration": 3,
    "targetDuration": 156
  },
  {
    "id": "types-of-houses-18",
    "title": "Types of Houses - Part 18",
    "bgGradient": [
      "#FF9800",
      "#FFE0B2"
    ],
    "accentColor": "#E65100",
    "items": [
      {
        "letter": "H",
        "word": "House",
        "emoji": "🏠",
        "bgColor": "#FF8F00"
      },
      {
        "letter": "A",
        "word": "Apartment",
        "emoji": "🏢",
        "bgColor": "#607D8B"
      },
      {
        "letter": "C",
        "word": "Cabin",
        "emoji": "🏡",
        "bgColor": "#795548"
      },
      {
        "letter": "C",
        "word": "Castle",
        "emoji": "🏰",
        "bgColor": "#607D8B"
      },
      {
        "letter": "I",
        "word": "Igloo",
        "emoji": "🏠",
        "bgColor": "#E0E0E0"
      },
      {
        "letter": "T",
        "word": "Tent",
        "emoji": "⛺",
        "bgColor": "#4CAF50"
      },
      {
        "letter": "M",
        "word": "Mansion",
        "emoji": "🏠",
        "bgColor": "#FFB300"
      },
      {
        "letter": "C",
        "word": "Cottage",
        "emoji": "🏡",
        "bgColor": "#4CAF50"
      },
      {
        "letter": "B",
        "word": "Bungalow",
        "emoji": "🏠",
        "bgColor": "#8D6E63"
      },
      {
        "letter": "F",
        "word": "Farmhouse",
        "emoji": "🏡",
        "bgColor": "#795548"
      },
      {
        "letter": "T",
        "word": "Treehouse",
        "emoji": "🌳",
        "bgColor": "#2E7D32"
      },
      {
        "letter": "H",
        "word": "Houseboat",
        "emoji": "🛥️",
        "bgColor": "#42A5F5"
      },
      {
        "letter": "P",
        "word": "Palace",
        "emoji": "🏰",
        "bgColor": "#FFD54F"
      },
      {
        "letter": "L",
        "word": "Lighthouse",
        "emoji": "🗼",
        "bgColor": "#D32F2F"
      },
      {
        "letter": "D",
        "word": "Duplex",
        "emoji": "🏘️",
        "bgColor": "#607D8B"
      }
    ],
    "letterDuration": 3,
    "introDuration": 3,
    "outroDuration": 3,
    "targetDuration": 132
  },
  {
    "id": "types-of-houses-19",
    "title": "Types of Houses - Part 19",
    "bgGradient": [
      "#795548",
      "#D7CCC8"
    ],
    "accentColor": "#3E2723",
    "items": [
      {
        "letter": "H",
        "word": "House",
        "emoji": "🏠",
        "bgColor": "#FF8F00"
      },
      {
        "letter": "A",
        "word": "Apartment",
        "emoji": "🏢",
        "bgColor": "#607D8B"
      },
      {
        "letter": "C",
        "word": "Cabin",
        "emoji": "🏡",
        "bgColor": "#795548"
      },
      {
        "letter": "C",
        "word": "Castle",
        "emoji": "🏰",
        "bgColor": "#607D8B"
      },
      {
        "letter": "I",
        "word": "Igloo",
        "emoji": "🏠",
        "bgColor": "#E0E0E0"
      },
      {
        "letter": "T",
        "word": "Tent",
        "emoji": "⛺",
        "bgColor": "#4CAF50"
      },
      {
        "letter": "M",
        "word": "Mansion",
        "emoji": "🏠",
        "bgColor": "#FFB300"
      },
      {
        "letter": "C",
        "word": "Cottage",
        "emoji": "🏡",
        "bgColor": "#4CAF50"
      },
      {
        "letter": "B",
        "word": "Bungalow",
        "emoji": "🏠",
        "bgColor": "#8D6E63"
      },
      {
        "letter": "F",
        "word": "Farmhouse",
        "emoji": "🏡",
        "bgColor": "#795548"
      },
      {
        "letter": "T",
        "word": "Treehouse",
        "emoji": "🌳",
        "bgColor": "#2E7D32"
      },
      {
        "letter": "H",
        "word": "Houseboat",
        "emoji": "🛥️",
        "bgColor": "#42A5F5"
      },
      {
        "letter": "P",
        "word": "Palace",
        "emoji": "🏰",
        "bgColor": "#FFD54F"
      },
      {
        "letter": "L",
        "word": "Lighthouse",
        "emoji": "🗼",
        "bgColor": "#D32F2F"
      },
      {
        "letter": "D",
        "word": "Duplex",
        "emoji": "🏘️",
        "bgColor": "#607D8B"
      }
    ],
    "letterDuration": 3,
    "introDuration": 3,
    "outroDuration": 3,
    "targetDuration": 158
  },
  {
    "id": "types-of-houses-20",
    "title": "Types of Houses - Part 20",
    "bgGradient": [
      "#42A5F5",
      "#BBDEFB"
    ],
    "accentColor": "#0D47A1",
    "items": [
      {
        "letter": "H",
        "word": "House",
        "emoji": "🏠",
        "bgColor": "#FF8F00"
      },
      {
        "letter": "A",
        "word": "Apartment",
        "emoji": "🏢",
        "bgColor": "#607D8B"
      },
      {
        "letter": "C",
        "word": "Cabin",
        "emoji": "🏡",
        "bgColor": "#795548"
      },
      {
        "letter": "C",
        "word": "Castle",
        "emoji": "🏰",
        "bgColor": "#607D8B"
      },
      {
        "letter": "I",
        "word": "Igloo",
        "emoji": "🏠",
        "bgColor": "#E0E0E0"
      },
      {
        "letter": "T",
        "word": "Tent",
        "emoji": "⛺",
        "bgColor": "#4CAF50"
      },
      {
        "letter": "M",
        "word": "Mansion",
        "emoji": "🏠",
        "bgColor": "#FFB300"
      },
      {
        "letter": "C",
        "word": "Cottage",
        "emoji": "🏡",
        "bgColor": "#4CAF50"
      },
      {
        "letter": "B",
        "word": "Bungalow",
        "emoji": "🏠",
        "bgColor": "#8D6E63"
      },
      {
        "letter": "F",
        "word": "Farmhouse",
        "emoji": "🏡",
        "bgColor": "#795548"
      },
      {
        "letter": "T",
        "word": "Treehouse",
        "emoji": "🌳",
        "bgColor": "#2E7D32"
      },
      {
        "letter": "H",
        "word": "Houseboat",
        "emoji": "🛥️",
        "bgColor": "#42A5F5"
      },
      {
        "letter": "P",
        "word": "Palace",
        "emoji": "🏰",
        "bgColor": "#FFD54F"
      },
      {
        "letter": "L",
        "word": "Lighthouse",
        "emoji": "🗼",
        "bgColor": "#D32F2F"
      },
      {
        "letter": "D",
        "word": "Duplex",
        "emoji": "🏘️",
        "bgColor": "#607D8B"
      }
    ],
    "letterDuration": 3,
    "introDuration": 3,
    "outroDuration": 3,
    "targetDuration": 133
  },
  {
    "id": "types-of-houses-21",
    "title": "Types of Houses - Part 21",
    "bgGradient": [
      "#FF9800",
      "#FFE0B2"
    ],
    "accentColor": "#E65100",
    "items": [
      {
        "letter": "H",
        "word": "House",
        "emoji": "🏠",
        "bgColor": "#FF8F00"
      },
      {
        "letter": "A",
        "word": "Apartment",
        "emoji": "🏢",
        "bgColor": "#607D8B"
      },
      {
        "letter": "C",
        "word": "Cabin",
        "emoji": "🏡",
        "bgColor": "#795548"
      },
      {
        "letter": "C",
        "word": "Castle",
        "emoji": "🏰",
        "bgColor": "#607D8B"
      },
      {
        "letter": "I",
        "word": "Igloo",
        "emoji": "🏠",
        "bgColor": "#E0E0E0"
      },
      {
        "letter": "T",
        "word": "Tent",
        "emoji": "⛺",
        "bgColor": "#4CAF50"
      },
      {
        "letter": "M",
        "word": "Mansion",
        "emoji": "🏠",
        "bgColor": "#FFB300"
      },
      {
        "letter": "C",
        "word": "Cottage",
        "emoji": "🏡",
        "bgColor": "#4CAF50"
      },
      {
        "letter": "B",
        "word": "Bungalow",
        "emoji": "🏠",
        "bgColor": "#8D6E63"
      },
      {
        "letter": "F",
        "word": "Farmhouse",
        "emoji": "🏡",
        "bgColor": "#795548"
      },
      {
        "letter": "T",
        "word": "Treehouse",
        "emoji": "🌳",
        "bgColor": "#2E7D32"
      },
      {
        "letter": "H",
        "word": "Houseboat",
        "emoji": "🛥️",
        "bgColor": "#42A5F5"
      },
      {
        "letter": "P",
        "word": "Palace",
        "emoji": "🏰",
        "bgColor": "#FFD54F"
      },
      {
        "letter": "L",
        "word": "Lighthouse",
        "emoji": "🗼",
        "bgColor": "#D32F2F"
      },
      {
        "letter": "D",
        "word": "Duplex",
        "emoji": "🏘️",
        "bgColor": "#607D8B"
      }
    ],
    "letterDuration": 3,
    "introDuration": 3,
    "outroDuration": 3,
    "targetDuration": 159
  },
  {
    "id": "types-of-houses-22",
    "title": "Types of Houses - Part 22",
    "bgGradient": [
      "#795548",
      "#D7CCC8"
    ],
    "accentColor": "#3E2723",
    "items": [
      {
        "letter": "H",
        "word": "House",
        "emoji": "🏠",
        "bgColor": "#FF8F00"
      },
      {
        "letter": "A",
        "word": "Apartment",
        "emoji": "🏢",
        "bgColor": "#607D8B"
      },
      {
        "letter": "C",
        "word": "Cabin",
        "emoji": "🏡",
        "bgColor": "#795548"
      },
      {
        "letter": "C",
        "word": "Castle",
        "emoji": "🏰",
        "bgColor": "#607D8B"
      },
      {
        "letter": "I",
        "word": "Igloo",
        "emoji": "🏠",
        "bgColor": "#E0E0E0"
      },
      {
        "letter": "T",
        "word": "Tent",
        "emoji": "⛺",
        "bgColor": "#4CAF50"
      },
      {
        "letter": "M",
        "word": "Mansion",
        "emoji": "🏠",
        "bgColor": "#FFB300"
      },
      {
        "letter": "C",
        "word": "Cottage",
        "emoji": "🏡",
        "bgColor": "#4CAF50"
      },
      {
        "letter": "B",
        "word": "Bungalow",
        "emoji": "🏠",
        "bgColor": "#8D6E63"
      },
      {
        "letter": "F",
        "word": "Farmhouse",
        "emoji": "🏡",
        "bgColor": "#795548"
      },
      {
        "letter": "T",
        "word": "Treehouse",
        "emoji": "🌳",
        "bgColor": "#2E7D32"
      },
      {
        "letter": "H",
        "word": "Houseboat",
        "emoji": "🛥️",
        "bgColor": "#42A5F5"
      },
      {
        "letter": "P",
        "word": "Palace",
        "emoji": "🏰",
        "bgColor": "#FFD54F"
      },
      {
        "letter": "L",
        "word": "Lighthouse",
        "emoji": "🗼",
        "bgColor": "#D32F2F"
      },
      {
        "letter": "D",
        "word": "Duplex",
        "emoji": "🏘️",
        "bgColor": "#607D8B"
      }
    ],
    "letterDuration": 3,
    "introDuration": 3,
    "outroDuration": 3,
    "targetDuration": 134
  },
  {
    "id": "types-of-houses-23",
    "title": "Types of Houses - Part 23",
    "bgGradient": [
      "#42A5F5",
      "#BBDEFB"
    ],
    "accentColor": "#0D47A1",
    "items": [
      {
        "letter": "H",
        "word": "House",
        "emoji": "🏠",
        "bgColor": "#FF8F00"
      },
      {
        "letter": "A",
        "word": "Apartment",
        "emoji": "🏢",
        "bgColor": "#607D8B"
      },
      {
        "letter": "C",
        "word": "Cabin",
        "emoji": "🏡",
        "bgColor": "#795548"
      },
      {
        "letter": "C",
        "word": "Castle",
        "emoji": "🏰",
        "bgColor": "#607D8B"
      },
      {
        "letter": "I",
        "word": "Igloo",
        "emoji": "🏠",
        "bgColor": "#E0E0E0"
      },
      {
        "letter": "T",
        "word": "Tent",
        "emoji": "⛺",
        "bgColor": "#4CAF50"
      },
      {
        "letter": "M",
        "word": "Mansion",
        "emoji": "🏠",
        "bgColor": "#FFB300"
      },
      {
        "letter": "C",
        "word": "Cottage",
        "emoji": "🏡",
        "bgColor": "#4CAF50"
      },
      {
        "letter": "B",
        "word": "Bungalow",
        "emoji": "🏠",
        "bgColor": "#8D6E63"
      },
      {
        "letter": "F",
        "word": "Farmhouse",
        "emoji": "🏡",
        "bgColor": "#795548"
      },
      {
        "letter": "T",
        "word": "Treehouse",
        "emoji": "🌳",
        "bgColor": "#2E7D32"
      },
      {
        "letter": "H",
        "word": "Houseboat",
        "emoji": "🛥️",
        "bgColor": "#42A5F5"
      },
      {
        "letter": "P",
        "word": "Palace",
        "emoji": "🏰",
        "bgColor": "#FFD54F"
      },
      {
        "letter": "L",
        "word": "Lighthouse",
        "emoji": "🗼",
        "bgColor": "#D32F2F"
      },
      {
        "letter": "D",
        "word": "Duplex",
        "emoji": "🏘️",
        "bgColor": "#607D8B"
      }
    ],
    "letterDuration": 3,
    "introDuration": 3,
    "outroDuration": 3,
    "targetDuration": 161
  },
  {
    "id": "types-of-houses-24",
    "title": "Types of Houses - Part 24",
    "bgGradient": [
      "#FF9800",
      "#FFE0B2"
    ],
    "accentColor": "#E65100",
    "items": [
      {
        "letter": "H",
        "word": "House",
        "emoji": "🏠",
        "bgColor": "#FF8F00"
      },
      {
        "letter": "A",
        "word": "Apartment",
        "emoji": "🏢",
        "bgColor": "#607D8B"
      },
      {
        "letter": "C",
        "word": "Cabin",
        "emoji": "🏡",
        "bgColor": "#795548"
      },
      {
        "letter": "C",
        "word": "Castle",
        "emoji": "🏰",
        "bgColor": "#607D8B"
      },
      {
        "letter": "I",
        "word": "Igloo",
        "emoji": "🏠",
        "bgColor": "#E0E0E0"
      },
      {
        "letter": "T",
        "word": "Tent",
        "emoji": "⛺",
        "bgColor": "#4CAF50"
      },
      {
        "letter": "M",
        "word": "Mansion",
        "emoji": "🏠",
        "bgColor": "#FFB300"
      },
      {
        "letter": "C",
        "word": "Cottage",
        "emoji": "🏡",
        "bgColor": "#4CAF50"
      },
      {
        "letter": "B",
        "word": "Bungalow",
        "emoji": "🏠",
        "bgColor": "#8D6E63"
      },
      {
        "letter": "F",
        "word": "Farmhouse",
        "emoji": "🏡",
        "bgColor": "#795548"
      },
      {
        "letter": "T",
        "word": "Treehouse",
        "emoji": "🌳",
        "bgColor": "#2E7D32"
      },
      {
        "letter": "H",
        "word": "Houseboat",
        "emoji": "🛥️",
        "bgColor": "#42A5F5"
      },
      {
        "letter": "P",
        "word": "Palace",
        "emoji": "🏰",
        "bgColor": "#FFD54F"
      },
      {
        "letter": "L",
        "word": "Lighthouse",
        "emoji": "🗼",
        "bgColor": "#D32F2F"
      },
      {
        "letter": "D",
        "word": "Duplex",
        "emoji": "🏘️",
        "bgColor": "#607D8B"
      }
    ],
    "letterDuration": 3,
    "introDuration": 3,
    "outroDuration": 3,
    "targetDuration": 136
  },
  {
    "id": "types-of-houses-25",
    "title": "Types of Houses - Part 25",
    "bgGradient": [
      "#795548",
      "#D7CCC8"
    ],
    "accentColor": "#3E2723",
    "items": [
      {
        "letter": "H",
        "word": "House",
        "emoji": "🏠",
        "bgColor": "#FF8F00"
      },
      {
        "letter": "A",
        "word": "Apartment",
        "emoji": "🏢",
        "bgColor": "#607D8B"
      },
      {
        "letter": "C",
        "word": "Cabin",
        "emoji": "🏡",
        "bgColor": "#795548"
      },
      {
        "letter": "C",
        "word": "Castle",
        "emoji": "🏰",
        "bgColor": "#607D8B"
      },
      {
        "letter": "I",
        "word": "Igloo",
        "emoji": "🏠",
        "bgColor": "#E0E0E0"
      },
      {
        "letter": "T",
        "word": "Tent",
        "emoji": "⛺",
        "bgColor": "#4CAF50"
      },
      {
        "letter": "M",
        "word": "Mansion",
        "emoji": "🏠",
        "bgColor": "#FFB300"
      },
      {
        "letter": "C",
        "word": "Cottage",
        "emoji": "🏡",
        "bgColor": "#4CAF50"
      },
      {
        "letter": "B",
        "word": "Bungalow",
        "emoji": "🏠",
        "bgColor": "#8D6E63"
      },
      {
        "letter": "F",
        "word": "Farmhouse",
        "emoji": "🏡",
        "bgColor": "#795548"
      },
      {
        "letter": "T",
        "word": "Treehouse",
        "emoji": "🌳",
        "bgColor": "#2E7D32"
      },
      {
        "letter": "H",
        "word": "Houseboat",
        "emoji": "🛥️",
        "bgColor": "#42A5F5"
      },
      {
        "letter": "P",
        "word": "Palace",
        "emoji": "🏰",
        "bgColor": "#FFD54F"
      },
      {
        "letter": "L",
        "word": "Lighthouse",
        "emoji": "🗼",
        "bgColor": "#D32F2F"
      },
      {
        "letter": "D",
        "word": "Duplex",
        "emoji": "🏘️",
        "bgColor": "#607D8B"
      }
    ],
    "letterDuration": 3,
    "introDuration": 3,
    "outroDuration": 3,
    "targetDuration": 162
  },
  {
    "id": "types-of-houses-26",
    "title": "Types of Houses - Part 26",
    "bgGradient": [
      "#42A5F5",
      "#BBDEFB"
    ],
    "accentColor": "#0D47A1",
    "items": [
      {
        "letter": "H",
        "word": "House",
        "emoji": "🏠",
        "bgColor": "#FF8F00"
      },
      {
        "letter": "A",
        "word": "Apartment",
        "emoji": "🏢",
        "bgColor": "#607D8B"
      },
      {
        "letter": "C",
        "word": "Cabin",
        "emoji": "🏡",
        "bgColor": "#795548"
      },
      {
        "letter": "C",
        "word": "Castle",
        "emoji": "🏰",
        "bgColor": "#607D8B"
      },
      {
        "letter": "I",
        "word": "Igloo",
        "emoji": "🏠",
        "bgColor": "#E0E0E0"
      },
      {
        "letter": "T",
        "word": "Tent",
        "emoji": "⛺",
        "bgColor": "#4CAF50"
      },
      {
        "letter": "M",
        "word": "Mansion",
        "emoji": "🏠",
        "bgColor": "#FFB300"
      },
      {
        "letter": "C",
        "word": "Cottage",
        "emoji": "🏡",
        "bgColor": "#4CAF50"
      },
      {
        "letter": "B",
        "word": "Bungalow",
        "emoji": "🏠",
        "bgColor": "#8D6E63"
      },
      {
        "letter": "F",
        "word": "Farmhouse",
        "emoji": "🏡",
        "bgColor": "#795548"
      },
      {
        "letter": "T",
        "word": "Treehouse",
        "emoji": "🌳",
        "bgColor": "#2E7D32"
      },
      {
        "letter": "H",
        "word": "Houseboat",
        "emoji": "🛥️",
        "bgColor": "#42A5F5"
      },
      {
        "letter": "P",
        "word": "Palace",
        "emoji": "🏰",
        "bgColor": "#FFD54F"
      },
      {
        "letter": "L",
        "word": "Lighthouse",
        "emoji": "🗼",
        "bgColor": "#D32F2F"
      },
      {
        "letter": "D",
        "word": "Duplex",
        "emoji": "🏘️",
        "bgColor": "#607D8B"
      }
    ],
    "letterDuration": 3,
    "introDuration": 3,
    "outroDuration": 3,
    "targetDuration": 137
  },
  {
    "id": "types-of-houses-27",
    "title": "Types of Houses - Part 27",
    "bgGradient": [
      "#FF9800",
      "#FFE0B2"
    ],
    "accentColor": "#E65100",
    "items": [
      {
        "letter": "H",
        "word": "House",
        "emoji": "🏠",
        "bgColor": "#FF8F00"
      },
      {
        "letter": "A",
        "word": "Apartment",
        "emoji": "🏢",
        "bgColor": "#607D8B"
      },
      {
        "letter": "C",
        "word": "Cabin",
        "emoji": "🏡",
        "bgColor": "#795548"
      },
      {
        "letter": "C",
        "word": "Castle",
        "emoji": "🏰",
        "bgColor": "#607D8B"
      },
      {
        "letter": "I",
        "word": "Igloo",
        "emoji": "🏠",
        "bgColor": "#E0E0E0"
      },
      {
        "letter": "T",
        "word": "Tent",
        "emoji": "⛺",
        "bgColor": "#4CAF50"
      },
      {
        "letter": "M",
        "word": "Mansion",
        "emoji": "🏠",
        "bgColor": "#FFB300"
      },
      {
        "letter": "C",
        "word": "Cottage",
        "emoji": "🏡",
        "bgColor": "#4CAF50"
      },
      {
        "letter": "B",
        "word": "Bungalow",
        "emoji": "🏠",
        "bgColor": "#8D6E63"
      },
      {
        "letter": "F",
        "word": "Farmhouse",
        "emoji": "🏡",
        "bgColor": "#795548"
      },
      {
        "letter": "T",
        "word": "Treehouse",
        "emoji": "🌳",
        "bgColor": "#2E7D32"
      },
      {
        "letter": "H",
        "word": "Houseboat",
        "emoji": "🛥️",
        "bgColor": "#42A5F5"
      },
      {
        "letter": "P",
        "word": "Palace",
        "emoji": "🏰",
        "bgColor": "#FFD54F"
      },
      {
        "letter": "L",
        "word": "Lighthouse",
        "emoji": "🗼",
        "bgColor": "#D32F2F"
      },
      {
        "letter": "D",
        "word": "Duplex",
        "emoji": "🏘️",
        "bgColor": "#607D8B"
      }
    ],
    "letterDuration": 3,
    "introDuration": 3,
    "outroDuration": 3,
    "targetDuration": 163
  },
  {
    "id": "types-of-houses-28",
    "title": "Types of Houses - Part 28",
    "bgGradient": [
      "#795548",
      "#D7CCC8"
    ],
    "accentColor": "#3E2723",
    "items": [
      {
        "letter": "H",
        "word": "House",
        "emoji": "🏠",
        "bgColor": "#FF8F00"
      },
      {
        "letter": "A",
        "word": "Apartment",
        "emoji": "🏢",
        "bgColor": "#607D8B"
      },
      {
        "letter": "C",
        "word": "Cabin",
        "emoji": "🏡",
        "bgColor": "#795548"
      },
      {
        "letter": "C",
        "word": "Castle",
        "emoji": "🏰",
        "bgColor": "#607D8B"
      },
      {
        "letter": "I",
        "word": "Igloo",
        "emoji": "🏠",
        "bgColor": "#E0E0E0"
      },
      {
        "letter": "T",
        "word": "Tent",
        "emoji": "⛺",
        "bgColor": "#4CAF50"
      },
      {
        "letter": "M",
        "word": "Mansion",
        "emoji": "🏠",
        "bgColor": "#FFB300"
      },
      {
        "letter": "C",
        "word": "Cottage",
        "emoji": "🏡",
        "bgColor": "#4CAF50"
      },
      {
        "letter": "B",
        "word": "Bungalow",
        "emoji": "🏠",
        "bgColor": "#8D6E63"
      },
      {
        "letter": "F",
        "word": "Farmhouse",
        "emoji": "🏡",
        "bgColor": "#795548"
      },
      {
        "letter": "T",
        "word": "Treehouse",
        "emoji": "🌳",
        "bgColor": "#2E7D32"
      },
      {
        "letter": "H",
        "word": "Houseboat",
        "emoji": "🛥️",
        "bgColor": "#42A5F5"
      },
      {
        "letter": "P",
        "word": "Palace",
        "emoji": "🏰",
        "bgColor": "#FFD54F"
      },
      {
        "letter": "L",
        "word": "Lighthouse",
        "emoji": "🗼",
        "bgColor": "#D32F2F"
      },
      {
        "letter": "D",
        "word": "Duplex",
        "emoji": "🏘️",
        "bgColor": "#607D8B"
      }
    ],
    "letterDuration": 3,
    "introDuration": 3,
    "outroDuration": 3,
    "targetDuration": 139
  },
  {
    "id": "types-of-houses-29",
    "title": "Types of Houses - Part 29",
    "bgGradient": [
      "#42A5F5",
      "#BBDEFB"
    ],
    "accentColor": "#0D47A1",
    "items": [
      {
        "letter": "H",
        "word": "House",
        "emoji": "🏠",
        "bgColor": "#FF8F00"
      },
      {
        "letter": "A",
        "word": "Apartment",
        "emoji": "🏢",
        "bgColor": "#607D8B"
      },
      {
        "letter": "C",
        "word": "Cabin",
        "emoji": "🏡",
        "bgColor": "#795548"
      },
      {
        "letter": "C",
        "word": "Castle",
        "emoji": "🏰",
        "bgColor": "#607D8B"
      },
      {
        "letter": "I",
        "word": "Igloo",
        "emoji": "🏠",
        "bgColor": "#E0E0E0"
      },
      {
        "letter": "T",
        "word": "Tent",
        "emoji": "⛺",
        "bgColor": "#4CAF50"
      },
      {
        "letter": "M",
        "word": "Mansion",
        "emoji": "🏠",
        "bgColor": "#FFB300"
      },
      {
        "letter": "C",
        "word": "Cottage",
        "emoji": "🏡",
        "bgColor": "#4CAF50"
      },
      {
        "letter": "B",
        "word": "Bungalow",
        "emoji": "🏠",
        "bgColor": "#8D6E63"
      },
      {
        "letter": "F",
        "word": "Farmhouse",
        "emoji": "🏡",
        "bgColor": "#795548"
      },
      {
        "letter": "T",
        "word": "Treehouse",
        "emoji": "🌳",
        "bgColor": "#2E7D32"
      },
      {
        "letter": "H",
        "word": "Houseboat",
        "emoji": "🛥️",
        "bgColor": "#42A5F5"
      },
      {
        "letter": "P",
        "word": "Palace",
        "emoji": "🏰",
        "bgColor": "#FFD54F"
      },
      {
        "letter": "L",
        "word": "Lighthouse",
        "emoji": "🗼",
        "bgColor": "#D32F2F"
      },
      {
        "letter": "D",
        "word": "Duplex",
        "emoji": "🏘️",
        "bgColor": "#607D8B"
      }
    ],
    "letterDuration": 3,
    "introDuration": 3,
    "outroDuration": 3,
    "targetDuration": 165
  },
  {
    "id": "types-of-houses-30",
    "title": "Types of Houses - Part 30",
    "bgGradient": [
      "#FF9800",
      "#FFE0B2"
    ],
    "accentColor": "#E65100",
    "items": [
      {
        "letter": "H",
        "word": "House",
        "emoji": "🏠",
        "bgColor": "#FF8F00"
      },
      {
        "letter": "A",
        "word": "Apartment",
        "emoji": "🏢",
        "bgColor": "#607D8B"
      },
      {
        "letter": "C",
        "word": "Cabin",
        "emoji": "🏡",
        "bgColor": "#795548"
      },
      {
        "letter": "C",
        "word": "Castle",
        "emoji": "🏰",
        "bgColor": "#607D8B"
      },
      {
        "letter": "I",
        "word": "Igloo",
        "emoji": "🏠",
        "bgColor": "#E0E0E0"
      },
      {
        "letter": "T",
        "word": "Tent",
        "emoji": "⛺",
        "bgColor": "#4CAF50"
      },
      {
        "letter": "M",
        "word": "Mansion",
        "emoji": "🏠",
        "bgColor": "#FFB300"
      },
      {
        "letter": "C",
        "word": "Cottage",
        "emoji": "🏡",
        "bgColor": "#4CAF50"
      },
      {
        "letter": "B",
        "word": "Bungalow",
        "emoji": "🏠",
        "bgColor": "#8D6E63"
      },
      {
        "letter": "F",
        "word": "Farmhouse",
        "emoji": "🏡",
        "bgColor": "#795548"
      },
      {
        "letter": "T",
        "word": "Treehouse",
        "emoji": "🌳",
        "bgColor": "#2E7D32"
      },
      {
        "letter": "H",
        "word": "Houseboat",
        "emoji": "🛥️",
        "bgColor": "#42A5F5"
      },
      {
        "letter": "P",
        "word": "Palace",
        "emoji": "🏰",
        "bgColor": "#FFD54F"
      },
      {
        "letter": "L",
        "word": "Lighthouse",
        "emoji": "🗼",
        "bgColor": "#D32F2F"
      },
      {
        "letter": "D",
        "word": "Duplex",
        "emoji": "🏘️",
        "bgColor": "#607D8B"
      }
    ],
    "letterDuration": 3,
    "introDuration": 3,
    "outroDuration": 3,
    "targetDuration": 140
  }
]